ebbflow/__init__.py
ebbflow/base_mechanistic_model.py
ebbflow-0.0.5.dist-info/METADATA
ebbflow-0.0.5.dist-info/WHEEL
ebbflow-0.0.5.dist-info/RECORD
