Metadata-Version: 2.1
Name: ebbflow
Version: 0.0.5
Summary: A template class for developing mechanistic models
License: MIT
Author: BFieguth
Author-email: bfieguth@uoguelph.ca
Requires-Python: >=3.12,<4.0
Classifier: License :: OSI Approved :: MIT License
Classifier: Programming Language :: Python :: 3
Classifier: Programming Language :: Python :: 3.12
Requires-Dist: numpy (>=2.1.1,<3.0.0)
Requires-Dist: pandas (>=2.2.2,<3.0.0)
Requires-Dist: scipy (>=1.14.1,<2.0.0)
